polity/__init__.py
polity/api.py
polity/static.py
polity-0.0.25.dist-info/LICENSE
polity-0.0.25.dist-info/METADATA
polity-0.0.25.dist-info/WHEEL
polity-0.0.25.dist-info/top_level.txt
polity-0.0.25.dist-info/RECORD
